{"name":"build-javascript","namedChunkGroups":{"polyfill":{"name":"polyfill","assets":[{"name":"webpack-runtime-7ed3d18af83b939244cd.js","size":5123},{"name":"polyfill-9a30836a24b301a5d76e.js","size":83481}],"filteredAssets":0,"assetsSize":88604,"filteredAuxiliaryAssets":2,"auxiliaryAssetsSize":223257},"app":{"name":"app","assets":[{"name":"webpack-runtime-7ed3d18af83b939244cd.js","size":5123},{"name":"styles.5ec4cbea4e1bbc6ed3f7.css","size":22942},{"name":"framework-ba3c1fe9e5b0c159c0a2.js","size":129724},{"name":"app-e9673cf493b40dcaf57b.js","size":150173}],"filteredAssets":0,"assetsSize":307962,"filteredAuxiliaryAssets":3,"auxiliaryAssetsSize":854410},"component---src-pages-404-tsx":{"name":"component---src-pages-404-tsx","assets":[{"name":"styles.5ec4cbea4e1bbc6ed3f7.css","size":22942},{"name":"commons-b6d06534a0f79af68d78.js","size":52146},{"name":"component---src-pages-404-tsx-b13d3e78681565fb918b.js","size":718}],"filteredAssets":0,"assetsSize":75806,"filteredAuxiliaryAssets":2,"auxiliaryAssetsSize":195647},"component---src-pages-index-tsx":{"name":"component---src-pages-index-tsx","assets":[{"name":"styles.5ec4cbea4e1bbc6ed3f7.css","size":22942},{"name":"commons-b6d06534a0f79af68d78.js","size":52146},{"name":"component---src-pages-index-tsx-37db67abb3120a94437c.js","size":2301}],"filteredAssets":0,"assetsSize":77389,"filteredAuxiliaryAssets":2,"auxiliaryAssetsSize":199392},"component---src-templates-blog-post-index-tsx":{"name":"component---src-templates-blog-post-index-tsx","assets":[{"name":"styles.5ec4cbea4e1bbc6ed3f7.css","size":22942},{"name":"commons-b6d06534a0f79af68d78.js","size":52146},{"name":"component---src-templates-blog-post-index-tsx-227ba44df3a4f6aa0141.js","size":4929}],"filteredAssets":0,"assetsSize":80017,"filteredAuxiliaryAssets":2,"auxiliaryAssetsSize":207898},"component---src-templates-tag-page-index-tsx":{"name":"component---src-templates-tag-page-index-tsx","assets":[{"name":"styles.5ec4cbea4e1bbc6ed3f7.css","size":22942},{"name":"commons-b6d06534a0f79af68d78.js","size":52146},{"name":"component---src-templates-tag-page-index-tsx-ea006b4711a6e2e433e5.js","size":2113}],"filteredAssets":0,"assetsSize":77201,"filteredAuxiliaryAssets":2,"auxiliaryAssetsSize":199223}},"assetsByChunkName":{"polyfill":["webpack-runtime-7ed3d18af83b939244cd.js","polyfill-9a30836a24b301a5d76e.js"],"app":["webpack-runtime-7ed3d18af83b939244cd.js","styles.5ec4cbea4e1bbc6ed3f7.css","framework-ba3c1fe9e5b0c159c0a2.js","app-e9673cf493b40dcaf57b.js"],"component---src-pages-404-tsx":["styles.5ec4cbea4e1bbc6ed3f7.css","commons-b6d06534a0f79af68d78.js","component---src-pages-404-tsx-b13d3e78681565fb918b.js"],"component---src-pages-index-tsx":["styles.5ec4cbea4e1bbc6ed3f7.css","commons-b6d06534a0f79af68d78.js","component---src-pages-index-tsx-37db67abb3120a94437c.js"],"component---src-templates-blog-post-index-tsx":["styles.5ec4cbea4e1bbc6ed3f7.css","commons-b6d06534a0f79af68d78.js","component---src-templates-blog-post-index-tsx-227ba44df3a4f6aa0141.js"],"component---src-templates-tag-page-index-tsx":["styles.5ec4cbea4e1bbc6ed3f7.css","commons-b6d06534a0f79af68d78.js","component---src-templates-tag-page-index-tsx-ea006b4711a6e2e433e5.js"]},"childAssetsByChunkName":{}}